Workbook
Name legenda_geral: Geral!#REF!

Sheet Geral
A1: DATA | B1: ÓRGÃO | C1: MUNICÍPIO | D1: TERRITÓRIO | E1: PLEITO | F1: ATO | G1: VALOR | H1: SITUAÇÃO
A2: Dezembro | B2: SESAB | C2: ABAIRA | D2: =_xlfn.XLOOKUP(Tabela1[[#This Row],[MUNICÍPIO]],referencias!C:C,referencias!B:B,"não consta") -> não consta | E2: REFORMA DO HOSPITAL ODIN MELLO | F2: CONVÊNIO | G2: 1170045.9 | H2: Ato dezembro Publicado
A3: Dezembro | B3: SESAB | C3: ABAIRA | D3: =_xlfn.XLOOKUP(Tabela1[[#This Row],[MUNICÍPIO]],referencias!C:C,referencias!B:B,"não consta") -> não consta | E3: CUSTEIO PARA AQUISIÇÃO DE MEDICAMENTOS E INSUMOS DO HOSPITAL MUNICIPAL ODIN MELLO | F3: CONVÊNIO | G3: 300000 | H3: Ato dezembro Publicado
A4: Dezembro | B4: SESAB | C4: ABARÉ | D4: =_xlfn.XLOOKUP(Tabela1[[#This Row],[MUNICÍPIO]],referencias!C:C,referencias!B:B,"não consta") -> ITAPARICA | E4: CONSTRUÇÃO DE UBS | F4: CONVÊNIO | G4: 1870068.6 | H4: Ato dezembro Publicado
A5: Dezembro | B5: SEC | C5: ABARÉ | D5: =_xlfn.XLOOKUP(Tabela1[[#This Row],[MUNICÍPIO]],referencias!C:C,referencias!B:B,"não consta") -> ITAPARICA | E5: AQUISIÇÃO DE MOBILIÁRIOS E MATERIAIS DE INFORMÁTICA | F5: CONVÊNIO | G5: 298921.65 | H5: Ato dezembro Publicado
A6: Dezembro | B6: SEC | C6: ABARÉ | D6: =_xlfn.XLOOKUP(Tabela1[[#This Row],[MUNICÍPIO]],referencias!C:C,referencias!B:B,"não consta") -> ITAPARICA | E6: REFORMA DA QUADRA MUNICIPAL PROFESSOR WALTER AUGUSTO JONES | F6: CONVÊNIO | G6: 246003.93 | H6: Ato dezembro Publicado
A7: Dezembro | B7: SEINFRA | C7: ÁGUA FRIA | D7: =_xlfn.XLOOKUP(Tabela1[[#This Row],[MUNICÍPIO]],referencias!C:C,referencias!B:B,"não consta") -> PORTAL DO SERTÃO | E7: CONSTRUÇÃO DE NOVA PONTE SOBRE O RIO INHAMBUPE, RODOVIA BA-084, TRECHO: PATAÍBA (ÁGUA FRIA) - BIRITINGA, KM 30,5 | F7: LICITAÇÃO | G7: 4410000 | H7: Ato dezembro Publicado
A8: Dezembro | B8: SEC | C8: ALAGOINHAS | D8: =_xlfn.XLOOKUP(Tabela1[[#This Row],[MUNICÍPIO]],referencias!C:C,referencias!B:B,"não consta") -> LITORAL NORTE E AGRESTE BAIANO | E8: CONSTRUÇÃO DE UMA ESCOLA COM 12 SALAS, COM QUADRA | F8: CONVÊNIO | G8: 10925311 | H8: Ato dezembro Publicado
A9: Dezembro | B9: SEC | C9: ALAGOINHAS | D9: =_xlfn.XLOOKUP(Tabela1[[#This Row],[MUNICÍPIO]],referencias!C:C,referencias!B:B,"não consta") -> LITORAL NORTE E AGRESTE BAIANO | E9: CONSTRUÇÃO DE CRECHE NO BAIRRO SANTA TEREZINHA | F9: CONVÊNIO | G9: 6899406.8 | H9: Ato dezembro Publicado
A10: Dezembro | B10: SEC | C10: ALAGOINHAS | D10: =_xlfn.XLOOKUP(Tabela1[[#This Row],[MUNICÍPIO]],referencias!C:C,referencias!B:B,"não consta") -> LITORAL NORTE E AGRESTE BAIANO | E10: AQUISIÇÃO DE MOBILIÁRIO PARA CRECHES MUNICIPAIS | F10: CONVÊNIO | G10: 299303.66 | H10: Ato dezembro Publicado
A11: Dezembro | B11: SEC | C11: ALAGOINHAS | D11: =_xlfn.XLOOKUP(Tabela1[[#This Row],[MUNICÍPIO]],referencias!C:C,referencias!B:B,"não consta") -> LITORAL NORTE E AGRESTE BAIANO | E11: EQUIPAMENTOS E MOBILIÁRIOS ESCOLAR | F11: CONVÊNIO | G11: 289694.53 | H11: Ato dezembro Publicado
A12: Dezembro | B12: SESAB | C12: ALAGOINHAS | D12: =_xlfn.XLOOKUP(Tabela1[[#This Row],[MUNICÍPIO]],referencias!C:C,referencias!B:B,"não consta") -> LITORAL NORTE E AGRESTE BAIANO | E12: REFORMA DE UBS | F12: CONVÊNIO | G12: 196000 | H12: Ato dezembro Publicado
A13: Dezembro | B13: SEC | C13: AMÉLIA RODRIGUES | D13: =_xlfn.XLOOKUP(Tabela1[[#This Row],[MUNICÍPIO]],referencias!C:C,referencias!B:B,"não consta") -> PORTAL DO SERTÃO | E13: AQUISIÇÃO DE EQUIPAMENTOS E MOBILIÁRIO ESCOLAR | F13: CONVÊNIO | G13: 199345.19 | H13: Ato dezembro Publicado
... A74: Dezembro | B74: SESAB | C74: CASTRO ALVES | D74: =_xlfn.XLOOKUP(Tabela1[[#This Row],[MUNICÍPIO]],referencias!C:C,referencias!B:B,"não consta") -> RECÔNCAVO | E74: REPARO DO TELHADO DO HOSPITAL MUNICIPAL | F74: CONVÊNIO | G74: 488235.28 | H74: Ato dezembro Publicado
B75: CONDER | C75: ACAJUTIBA | D75: =_xlfn.XLOOKUP(Tabela1[[#This Row],[MUNICÍPIO]],referencias!C:C,referencias!B:B,"não consta") -> LITORAL NORTE E AGRESTE BAIANO | E75: PAVIMENTAÇÃO EM PARALELEPÍPEDO E CALÇADA DA RUA GÓES CALMON NA SEDE | F75: INAUGURADA | G75: 1643720.2 | H75: ATENDIDO
A76: Dezembro | B76: CAR | C76: CHORROCHO | D76: =_xlfn.XLOOKUP(Tabela1[[#This Row],[MUNICÍPIO]],referencias!C:C,referencias!B:B,"não consta") -> não consta | E76: REFORMA DO MERCADO MUNICIPAL EM BARRA TARRACHIL | F76: CONVÊNIO | G76: 2500009.4 | H76: Ato dezembro Publicado
A77: Dezembro | B77: EMBASA | C77: CONCEIÇÃO DO ALMEIDA | D77: =_xlfn.XLOOKUP(Tabela1[[#This Row],[MUNICÍPIO]],referencias!C:C,referencias!B:B,"não consta") -> RECÔNCAVO | E77: PROJETO DE DUPLICAÇÃO DA ADUTORA DE CRUZ DAS ALMAS (CAJÁ) ATÉ SAPEAÇU/CONCEIÇÃO DO ALMEIDA | F77: CONTRATO | G77: 7300000 | H77: Ato dezembro Publicado
A78: Dezembro | B78: EMBASA | C78: CONDEÚBA | D78: =_xlfn.XLOOKUP(Tabela1[[#This Row],[MUNICÍPIO]],referencias!C:C,referencias!B:B,"não consta") -> SUDOESTE BAIANO | E78: IMPLANTAÇÃO DE SAA (REDE DE DISTRIBUIÇÃO E LIGAÇÕES) PARA OS POVOADOS DE MANGARITO, MANDACARU E BOA VISTA | F78: CONTRATO | G78: 1873376.3 | H78: Ato dezembro Publicado
A79: Dezembro | B79: SEINFRA | C79: COTEGIPE | D79: =_xlfn.XLOOKUP(Tabela1[[#This Row],[MUNICÍPIO]],referencias!C:C,referencias!B:B,"não consta") -> BACIA DO RIO GRANDE | E79: CONSTRUÇÃO DE 02 PONTES NO TRECHO SOBRE O RIACHO DO VEREDA NA BA-449, DISTRITO DE JUPAGUÁ (KM 49 E KM 50). Vão 50 e 30m. Comunidade Aguapiranga. | F79: LICITAÇÃO | G79: 9231281.3 | H79: Ato dezembro Publicado
A80: Dezembro | B80: SEINFRA | C80: CRAVOLÂNDIA | D80: =_xlfn.XLOOKUP(Tabela1[[#This Row],[MUNICÍPIO]],referencias!C:C,referencias!B:B,"não consta") -> VALE DO JIQUIRIÇÁ | E80: PAVIMENTAÇÃO CBUQ BR-420 - CRAVOLÂNDIA | F80: LICITAÇÃO | G80: 9100000 | H80: Ato dezembro Publicado
A81: Dezembro | B81: SEC | C81: CRAVOLÂNDIA | D81: =_xlfn.XLOOKUP(Tabela1[[#This Row],[MUNICÍPIO]],referencias!C:C,referencias!B:B,"não consta") -> VALE DO JIQUIRIÇÁ | E81: CONSTRUÇÃO DE UMA CRECHE NA SEDE | F81: CONVÊNIO | G81: 5889380 | H81: Ato dezembro Publicado
A82: Dezembro | B82: SEINFRA | C82: CURAÇA | D82: =_xlfn.XLOOKUP(Tabela1[[#This Row],[MUNICÍPIO]],referencias!C:C,referencias!B:B,"não consta") -> SERTÃO DO SÃO FRANCISCO | E82: RESTAURAÇÃO E DUPLICAÇÃO DA PAVIMENTAÇÃO EM TSD E CICLOFAIXA, TRECHO: ENTROCAMENTO DA BA-120 - CURAÇÁ | F82: Licitação | G82: 7477866.4 | H82: Ato dezembro Publicado
A83: Dezembro | B83: CAR | C83: CURAÇA | D83: =_xlfn.XLOOKUP(Tabela1[[#This Row],[MUNICÍPIO]],referencias!C:C,referencias!B:B,"não consta") -> SERTÃO DO SÃO FRANCISCO | E83: REQUALIFICAÇÃO DO MERCADO | F83: CONVÊNIO | G83: 1875541.2 | H83: Ato dezembro Publicado
A84: Dezembro | B84: SEINFRA | C84: DIAS D'AVILA | D84: =_xlfn.XLOOKUP(Tabela1[[#This Row],[MUNICÍPIO]],referencias!C:C,referencias!B:B,"não consta") -> METROPOLITANO DE SALVADOR | E84: PAVIMENTAÇÃO EM CBUQ DO TRECHO: ENTROCAMENTO BA-512 - ACESSO BARRAGEM SANTA HELENA | F84: Licitação | G84: 7690000 | H84: Ato dezembro Publicado
A85: Dezembro | B85: SEC | C85: DIAS D'AVILA | D85: =_xlfn.XLOOKUP(Tabela1[[#This Row],[MUNICÍPIO]],referencias!C:C,referencias!B:B,"não consta") -> METROPOLITANO DE SALVADOR | E85: AQUISIÇÃO DE EQUIPAMENTOS E MOBILIÁRIO ESCOLAR | F85: CONVÊNIO | G85: 167386.6 | H85: Ato dezembro Publicado
A86: Dezembro | B86: SEC | C86: DIAS D'AVILA | D86: =_xlfn.XLOOKUP(Tabela1[[#This Row],[MUNICÍPIO]],referencias!C:C,referencias!B:B,"não consta") -> METROPOLITANO DE SALVADOR | E86: AQUISIÇÃO DE EQUIPAMENTOS E MOBILIÁRIO ESCOLAR | F86: CONVÊNIO | G86: 144286.74 | H86: Ato dezembro Publicado
A87: Dezembro | B87: CERB | C87: DOM BASILIO | D87: =_xlfn.XLOOKUP(Tabela1[[#This Row],[MUNICÍPIO]],referencias!C:C,referencias!B:B,"não consta") -> SERTÃO PRODUTIVO | E87: IMPLANTAÇÃO DO SIAA - SISTEMA INTEGRADO DE ABASTECIMENTO DE ÁGUA NAS LOCALIDADES DE: SANTA LUZIA, TABUÁ, MORRO DO ENGENHO, ITAPICURU, LAGOA DO MORRO, CAIÇARA DO PIO, LAGOA COMPRIDA, POÇA DO OSÓRIO, LARANJO, PEIXE, ITAPICURU II, FAZENDINHA, CAIÇARA DA BARR | F87: CONTRATO | G87: 9319252.1 | H87: Ato dezembro Publicado
... A94: Dezembro | B94: SESAB | C94: GONGOGI | D94: =_xlfn.XLOOKUP(Tabela1[[#This Row],[MUNICÍPIO]],referencias!C:C,referencias!B:B,"não consta") -> MÉDIO RIO DE CONTAS | E94: CONSTRUÇÃO DE UBS | F94: CONVÊNIO | G94: 1870068.6 | H94: Ato dezembro Publicado
A95: 46174 | B95: CONDER | C95: ACAJUTIBA | D95: =_xlfn.XLOOKUP(Tabela1[[#This Row],[MUNICÍPIO]],referencias!C:C,referencias!B:B,"não consta") -> LITORAL NORTE E AGRESTE BAIANO | E95: CONSTRUÇÃO DA PRAÇA LAGOA SECA | F95: CONVÊNIO | G95: 278055.3 | H95: Ato junho publicado
A96: Dezembro | B96: SEC | C96: HELIÓPOLIS | D96: =_xlfn.XLOOKUP(Tabela1[[#This Row],[MUNICÍPIO]],referencias!C:C,referencias!B:B,"não consta") -> SEMIÁRIDO NORDESTE II | E96: REFORMA E AMPLIAÇÃO DA ESCOLA DOM PEDRO PRIMEIRO | F96: CONVÊNIO | G96: 3484341.4 | H96: Ato dezembro Publicado
A97: 46174 | B97: CONDER | C97: ACAJUTIBA | D97: =_xlfn.XLOOKUP(Tabela1[[#This Row],[MUNICÍPIO]],referencias!C:C,referencias!B:B,"não consta") -> LITORAL NORTE E AGRESTE BAIANO | E97: CONSTUÇÃO DA PRAÇA CANATUBIÁ | F97: CONVÊNIO | G97: 326174.07 | H97: Ato junho publicado
A98: 46174 | B98: CONDER | C98: ACAJUTIBA | D98: =_xlfn.XLOOKUP(Tabela1[[#This Row],[MUNICÍPIO]],referencias!C:C,referencias!B:B,"não consta") -> LITORAL NORTE E AGRESTE BAIANO | E98: CONSTRUÇÃO DA PRAÇA TIJUCO | F98: CONVÊNIO | G98: 373148.63 | H98: Ato junho publicado
A99: Dezembro | B99: SEC | C99: IBIPEBA | D99: =_xlfn.XLOOKUP(Tabela1[[#This Row],[MUNICÍPIO]],referencias!C:C,referencias!B:B,"não consta") -> IRECÊ | E99: AQUISIÇÃO DE INSTRUMENTOS MUSICAIS (FANFARRA) | F99: CONVÊNIO | G99: 195949.12 | H99: Ato dezembro Publicado
A100: Dezembro | B100: SEC | C100: IBIPEBA | D100: =_xlfn.XLOOKUP(Tabela1[[#This Row],[MUNICÍPIO]],referencias!C:C,referencias!B:B,"não consta") -> IRECÊ | E100: AQUISIÇÃO DE EQUIPAMENTOS E MOBILIÁRIO ESCOLAR | F100: CONVÊNIO | G100: 110325.14 | H100: Ato dezembro Publicado
A101: Dezembro | B101: SEC | C101: IBIRATAIA | D101: =_xlfn.XLOOKUP(Tabela1[[#This Row],[MUNICÍPIO]],referencias!C:C,referencias!B:B,"não consta") -> MÉDIO RIO DE CONTAS | E101: AQUISIÇÃO DE EQUIPAMENTOS E MOBILIÁRIOS ESCOLAR (INFANTIS) | F101: CONVÊNIO | G101: 373699.56 | H101: Ato dezembro Publicado
A102: Dezembro | B102: SEC | C102: IBOTIRAMA | D102: =_xlfn.XLOOKUP(Tabela1[[#This Row],[MUNICÍPIO]],referencias!C:C,referencias!B:B,"não consta") -> VELHO CHICO | E102: CONSTRUÇÃO DE UMA ESCOLA COM 6 SALAS, COM QUADRA POLIESPORTIVA COBERTA, NO BAIRRO JARDIM IMPERIAL | F102: CONVÊNIO | G102: 5036196.8 | H102: Ato dezembro Publicado
A103: 46174 | B103: CONDER | C103: ACAJUTIBA | D103: =_xlfn.XLOOKUP(Tabela1[[#This Row],[MUNICÍPIO]],referencias!C:C,referencias!B:B,"não consta") -> LITORAL NORTE E AGRESTE BAIANO | E103: CONSTRUÇÃO DA PRAÇA GANCHO DO BADOGUE | F103: CONVÊNIO | G103: 362296.08 | H103: Ato junho publicado
A104: 46174 | B104: CONDER | C104: ACAJUTIBA | D104: =_xlfn.XLOOKUP(Tabela1[[#This Row],[MUNICÍPIO]],referencias!C:C,referencias!B:B,"não consta") -> LITORAL NORTE E AGRESTE BAIANO | E104: CONSTRUÇÃO DA PRAÇA CRUZEIRO | F104: CONVÊNIO | G104: 465548.44 | H104: Ato junho publicado
A105: Dezembro | B105: CAR | C105: ICHU | D105: =_xlfn.XLOOKUP(Tabela1[[#This Row],[MUNICÍPIO]],referencias!C:C,referencias!B:B,"não consta") -> SISAL | E105: Reconstrução do Mercado Municipal | F105: CONVÊNIO | G105: 2000138.1 | H105: Ato dezembro Publicado
A106: Dezembro | B106: SEC | C106: INHAMBUPE | D106: =_xlfn.XLOOKUP(Tabela1[[#This Row],[MUNICÍPIO]],referencias!C:C,referencias!B:B,"não consta") -> LITORAL NORTE E AGRESTE BAIANO | E106: AQUISIÇÃO DE EQUIPAMENTOS E MOBILIÁRIO PARA A CRECHE | F106: CONVÊNIO | G106: 419279.27 | H106: Ato dezembro Publicado
A107: Dezembro | B107: SEINFRA | C107: IPECAETA | D107: =_xlfn.XLOOKUP(Tabela1[[#This Row],[MUNICÍPIO]],referencias!C:C,referencias!B:B,"não consta") -> não consta | E107: Recuperação da Pavimentação em TSD. RODOVIA: BA.120 TRECHO: Cavunge (Ipecaetá) – Entronc. BA-052. EXTENSÃO: 7,47km | F107: LICITAÇÃO | G107: 8023220.6 | H107: Ato dezembro Publicado
A108: Dezembro | B108: SEINFRA | C108: IPIRA | D108: =_xlfn.XLOOKUP(Tabela1[[#This Row],[MUNICÍPIO]],referencias!C:C,referencias!B:B,"não consta") -> não consta | E108: PAVIMENTAÇÃO EM TSD - ENTR. BA-052 - ACESSO AO POVOADO CORAÇÃO DE MARIA, MUNICÍPIO DE IPIRÁ. | F108: LICITAÇÃO | G108: 16012956 | H108: Ato dezembro Publicado
A109: Dezembro | B109: CAR | C109: IPUPIARA | D109: =_xlfn.XLOOKUP(Tabela1[[#This Row],[MUNICÍPIO]],referencias!C:C,referencias!B:B,"não consta") -> IRECÊ | E109: CONSTRUÇÃO DE MERCADO MUNICIPAL | F109: CONVÊNIO | G109: 2574601.8 | H109: Ato dezembro Publicado
A110: Dezembro | B110: SEINFRA | C110: IPUPIARA | D110: =_xlfn.XLOOKUP(Tabela1[[#This Row],[MUNICÍPIO]],referencias!C:C,referencias!B:B,"não consta") -> IRECÊ | E110: PAVIMENTAÇÃO EM TSD DO TRECHO: SEDE À VILA IBIPETUM | F110: CONTRATO | G110: 2400000 | H110: Ato dezembro Publicado
A111: 46174 | B111: CONDER | C111: ACAJUTIBA | D111: =_xlfn.XLOOKUP(Tabela1[[#This Row],[MUNICÍPIO]],referencias!C:C,referencias!B:B,"não consta") -> LITORAL NORTE E AGRESTE BAIANO | E111: CONSTRUÇÃO DA PRAÇA BENEDITO | F111: CONVÊNIO | G111: 327620.06 | H111: Ato junho publicado
A112: Dezembro | B112: CAR | C112: IRAJUBA | D112: =_xlfn.XLOOKUP(Tabela1[[#This Row],[MUNICÍPIO]],referencias!C:C,referencias!B:B,"não consta") -> VALE DO JIQUIRIÇÁ | E112: PASSAGEM MOLHADA DE MORAES | F112: CONVÊNIO | G112: 590000 | H112: Ato dezembro Publicado
A113: Março | B113: CONDER | C113: ADUSTINA | D113: =_xlfn.XLOOKUP(Tabela1[[#This Row],[MUNICÍPIO]],referencias!C:C,referencias!B:B,"não consta") -> SEMIÁRIDO NORDESTE II | E113: PAVIMENTAÇÃO ASFÁLTICA COM (CBUQ) SOBRE PAVIMENTO EXISTENTE EM PARALELEPÍPEDOS | F113: CONVÊNIO | G113: 3157298.4 | H113: ato março publicado
A114: Dezembro | B114: CAR | C114: IRECE | D114: =_xlfn.XLOOKUP(Tabela1[[#This Row],[MUNICÍPIO]],referencias!C:C,referencias!B:B,"não consta") -> não consta | E114: AMPLIAÇÃO DA ÁREA EXTERNA DO MERCADO MUNICIPAL DE IRECÊ | F114: CONVÊNIO | G114: 5399128 | H114: Ato dezembro Publicado
A115: Dezembro | B115: SEC | C115: ITACARÉ | D115: =_xlfn.XLOOKUP(Tabela1[[#This Row],[MUNICÍPIO]],referencias!C:C,referencias!B:B,"não consta") -> LITORAL SUL | E115: AQUISIÇÃO DE EQUIPAMENTOS E MOBILIÁRIO ESCOLAR | F115: CONVÊNIO | G115: 181614.13 | H115: Ato dezembro Publicado
A116: Dezembro | B116: SEC | C116: ITAGUAÇU DA BAHIA | D116: =_xlfn.XLOOKUP(Tabela1[[#This Row],[MUNICÍPIO]],referencias!C:C,referencias!B:B,"não consta") -> IRECÊ | E116: AQUISIÇÃO DE EQUIPAMENTOS E MOBILIÁRIO ESCOLAR | F116: CONVÊNIO | G116: 536337.41 | H116: Ato dezembro Publicado
A117: Março | B117: CONDER | C117: ADUSTINA | D117: =_xlfn.XLOOKUP(Tabela1[[#This Row],[MUNICÍPIO]],referencias!C:C,referencias!B:B,"não consta") -> SEMIÁRIDO NORDESTE II | E117: PAVIMENTAÇÃO ASFÁLTICA EM DIVERSAS RUAS NA SEDE | F117: CONVÊNIO | G117: 1466310.3 | H117: ato março publicado
A118: Dezembro | B118: SEC | C118: ITAMBÉ | D118: =_xlfn.XLOOKUP(Tabela1[[#This Row],[MUNICÍPIO]],referencias!C:C,referencias!B:B,"não consta") -> MÉDIO SUDOESTE DA BAHIA | E118: AQUISIÇÃO DE EQUIPAMENTOS E MOBILIÁRIO ESCOLAR | F118: CONVÊNIO | G118: 149634.22 | H118: Ato dezembro Publicado
A119: Dezembro | B119: SEC | C119: ITAMBÉ | D119: =_xlfn.XLOOKUP(Tabela1[[#This Row],[MUNICÍPIO]],referencias!C:C,referencias!B:B,"não consta") -> MÉDIO SUDOESTE DA BAHIA | E119: AQUISIÇÃO DE EQUIPAMENTOS E MOBILIÁRIOS | F119: CONVÊNIO | G119: 48913.08 | H119: Ato dezembro Publicado
A120: Dezembro | B120: SEINFRA | C120: ITANAGRA | D120: =_xlfn.XLOOKUP(Tabela1[[#This Row],[MUNICÍPIO]],referencias!C:C,referencias!B:B,"não consta") -> LITORAL NORTE E AGRESTE BAIANO | E120: PAVIMENTAÇÃO CBUQ NÚCLEO JK - PONTE DO RIO POJUCA. (SÃO JOSÉ DO AVENA) | F120: LICITAÇÃO | G120: 36310000 | H120: Ato dezembro Publicado
A121: SERIN | B121: CONDER | C121: ADUSTINA | D121: =_xlfn.XLOOKUP(Tabela1[[#This Row],[MUNICÍPIO]],referencias!C:C,referencias!B:B,"não consta") -> SEMIÁRIDO NORDESTE II | E121: Construção de uma Unidade de Saúde da Família com Sala de Estabilização no Município de Adustina. | F121: CONVÊNIO | G121: 4846850.7 | H121: ATENDIDO
A122: Dezembro | B122: SESAB | C122: ITIUBA | D122: =_xlfn.XLOOKUP(Tabela1[[#This Row],[MUNICÍPIO]],referencias!C:C,referencias!B:B,"não consta") -> não consta | E122: Construção Unidade Básica de Saúde – UBS no Povoado de Picos | F122: CONVÊNIO | G122: 1870068.6 | H122: Ato dezembro Publicado
A123: Dezembro | B123: SEC | C123: ITORORO | D123: =_xlfn.XLOOKUP(Tabela1[[#This Row],[MUNICÍPIO]],referencias!C:C,referencias!B:B,"não consta") -> não consta | E123: AQUISIÇÃO DE EQUIPAMENTOS E MOBILIÁRIO ESCOLAR | F123: CONVÊNIO | G123: 101338.22 | H123: Ato dezembro Publicado
A124: Dezembro | B124: CERB | C124: JAGUARARI | D124: =_xlfn.XLOOKUP(Tabela1[[#This Row],[MUNICÍPIO]],referencias!C:C,referencias!B:B,"não consta") -> PIEMONTE NORTE DO ITAPICURU | E124: IMPLANTAÇÃO DO SAA - SISTEMA ADUTOR DE ABASTECIMENTO DE ÁGUA NAS LOCALIDADES DE: ASSENTAMENTO FLAMENGO, ALAGADIÇO DO FLAMENGO E BARRINHA | G124: 9569730.1 | H124: Ato dezembro Publicado
A125: Dezembro | B125: SEINFRA | C125: JAGUARIPE | D125: =_xlfn.XLOOKUP(Tabela1[[#This Row],[MUNICÍPIO]],referencias!C:C,referencias!B:B,"não consta") -> BAIXO SUL | E125: PAVIMENTAÇÃO EM CBUQ DO ENTROCAMENTO BA-001 - ACESSO AO DISTRITO DE PALMA | F125: CONTRATO | G125: 27000000 | H125: Ato dezembro Publicado
A126: Dezembro | B126: SEC | C126: JANDAIRA | D126: =_xlfn.XLOOKUP(Tabela1[[#This Row],[MUNICÍPIO]],referencias!C:C,referencias!B:B,"não consta") -> LITORAL NORTE E AGRESTE BAIANO | E126: AMPLIAÇÃO DA ESCOLA MUNICIPAL JOANA ALMEIDA PINTO, COM 7 SALAS | F126: CONVÊNIO | G126: 711909.51 | H126: Ato dezembro Publicado
A127: Dezembro | B127: SEC | C127: JANDAIRA | D127: =_xlfn.XLOOKUP(Tabela1[[#This Row],[MUNICÍPIO]],referencias!C:C,referencias!B:B,"não consta") -> LITORAL NORTE E AGRESTE BAIANO | E127: AQUISIÇÃO DE ELETRODOMÉSTICO E MOBILIÁRIOS ESCOLAR | F127: CONVÊNIO | G127: 299606.97 | H127: Ato dezembro Publicado
A128: Dezembro | B128: SEC | C128: JANDAIRA | D128: =_xlfn.XLOOKUP(Tabela1[[#This Row],[MUNICÍPIO]],referencias!C:C,referencias!B:B,"não consta") -> LITORAL NORTE E AGRESTE BAIANO | E128: AQUISIÇÃO DE EQUIPAMENTOS (COMPUTADORES E IMPRESSORAS) E MOBILIÁRIO ESCOLAR | F128: CONVÊNIO | G128: 168958.67 | H128: Ato dezembro Publicado
A129: VISITA AO MUNICÍPIO | B129: CONDER | C129: ADUSTINA | D129: =_xlfn.XLOOKUP(Tabela1[[#This Row],[MUNICÍPIO]],referencias!C:C,referencias!B:B,"não consta") -> SEMIÁRIDO NORDESTE II | E129: PAVIMENTAÇÃO EM PARALELEPÍPEDO NO ENTORNO DO COLÉGIO ESTADUAL DE TEMPO INTEGRAL CASTRO ALVES | F129: Inaugura | G129: 252684.32 | H129: ATENDIDO
A130: 46174 | B130: CONDER | C130: ADUSTINA | D130: =_xlfn.XLOOKUP(Tabela1[[#This Row],[MUNICÍPIO]],referencias!C:C,referencias!B:B,"não consta") -> SEMIÁRIDO NORDESTE II | E130: PAVIMENTAÇÃO ASFÁLTICA SOBRE PARALELEPÍPEDO COM DRENAGEM SUPERFICIAL, EM RUAS DA SEDE DO MUNICÍPIO DE ADUSTINA, BA | F130: CONVÊNIO | G130: 3197240.5 | H130: Ato junho publicado
A131: 46174 | B131: CONDER | C131: ADUSTINA | D131: =_xlfn.XLOOKUP(Tabela1[[#This Row],[MUNICÍPIO]],referencias!C:C,referencias!B:B,"não consta") -> SEMIÁRIDO NORDESTE II | E131: PAVIMENTAÇÃO EM PARALELEPÍPEDO COM DRENAGEM SUPERFICIAL, EM VIAS URBANAS NO MUNICÍPIO DE ADUSTINA, BA | F131: CONVÊNIO | G131: 5282210.4 | H131: Ato junho publicado
A132: Dezembro | B132: SEINFRA | C132: JOAO DOURADO | D132: =_xlfn.XLOOKUP(Tabela1[[#This Row],[MUNICÍPIO]],referencias!C:C,referencias!B:B,"não consta") -> IRECÊ | E132: ESTRADA DA DESCOBERTA - UFV - IRECÊ (MUNICÍPIO DENJOÃO DOURADO), EXTENSÃO 19,91 KM | F132: LICITAÇÃO | G132: 19910000 | H132: Ato dezembro Publicado
A133: Dezembro | B133: CAR | C133: JUAZEIRO | D133: =_xlfn.XLOOKUP(Tabela1[[#This Row],[MUNICÍPIO]],referencias!C:C,referencias!B:B,"não consta") -> SERTÃO DO SÃO FRANCISCO | E133: CONSTRUÇÃO DO MERCADO DO PEIXE | F133: CONVÊNIO | G133: 1857585.5 | H133: Ato dezembro Publicado
A134: Dezembro | B134: CAR | C134: JUAZEIRO | D134: =_xlfn.XLOOKUP(Tabela1[[#This Row],[MUNICÍPIO]],referencias!C:C,referencias!B:B,"não consta") -> SERTÃO DO SÃO FRANCISCO | E134: Contrução do mercado do Distrito Maniçoba | F134: CONVÊNIO | G134: 2075227 | H134: Ato dezembro Publicado
A135: Dezembro | B135: SEC | C135: JUAZEIRO | D135: =_xlfn.XLOOKUP(Tabela1[[#This Row],[MUNICÍPIO]],referencias!C:C,referencias!B:B,"não consta") -> SERTÃO DO SÃO FRANCISCO | E135: AQUISIÇÃO DE INSTRUMENTOS MUSICAIS (FANFARRA) | F135: CONVÊNIO | G135: 158421.92 | H135: Ato dezembro Publicado
A136: Dezembro | B136: SEC | C136: JUSSARI | D136: =_xlfn.XLOOKUP(Tabela1[[#This Row],[MUNICÍPIO]],referencias!C:C,referencias!B:B,"não consta") -> LITORAL SUL | E136: REFORMA DO CENTRO DE ASSISTÊNCIA MULTIDISCIPLINAR | F136: CONVÊNIO | G136: 1765222.6 | H136: Ato dezembro Publicado
A137: Dezembro | B137: SESAB | C137: LAURO DE FREITAS | D137: =_xlfn.XLOOKUP(Tabela1[[#This Row],[MUNICÍPIO]],referencias!C:C,referencias!B:B,"não consta") -> METROPOLITANO DE SALVADOR | E137: Equipamentos de saúde | F137: CESSÃO | G137: 0 | H137: Ato dezembro Publicado
A138: Dezembro | B138: EMBASA | C138: LENCOIS | D138: =_xlfn.XLOOKUP(Tabela1[[#This Row],[MUNICÍPIO]],referencias!C:C,referencias!B:B,"não consta") -> não consta | E138: EXECUÇÃO DAS OBRAS DE AMPLIAÇÃO DO SES - SISTEMA DE ESGOTAMENTO SANITÁRIO | F138: CONTRATO | G138: 51472870 | H138: Ato dezembro Publicado
A139: Dezembro | B139: CAR | C139: LICINIO DE ALMEIDA | D139: =_xlfn.XLOOKUP(Tabela1[[#This Row],[MUNICÍPIO]],referencias!C:C,referencias!B:B,"não consta") -> não consta | E139: CONSTRUÇÃO DO MERCADO MUNICIPAL NO DISTRITO DE TAUAPÉ | F139: CONVÊNIO | G139: 1397170.7 | H139: Ato dezembro Publicado
A140: Dezembro | B140: SESAB | C140: LICINIO DE ALMEIDA | D140: =_xlfn.XLOOKUP(Tabela1[[#This Row],[MUNICÍPIO]],referencias!C:C,referencias!B:B,"não consta") -> não consta | E140: REFORMA DO HOSPITAL MUNICIPAL | F140: CONVÊNIO | G140: 799694.66 | H140: Ato dezembro Publicado
A141: Dezembro | B141: EMBASA | C141: LIVRAMENTO DE NOSSA SENHORA | D141: =_xlfn.XLOOKUP(Tabela1[[#This Row],[MUNICÍPIO]],referencias!C:C,referencias!B:B,"não consta") -> SERTÃO PRODUTIVO | E141: EXECUÇÃO DAS OBRAS DE IMPLANTAÇÃO DO SISTEMA DE ESGOTAMENTO SANITÁRIO | F141: CONTRATO | G141: 1.3982448e+08 | H141: Ato dezembro Publicado
A142: Dezembro | B142: CERB | C142: LIVRAMENTO DE NOSSA SENHORA | D142: =_xlfn.XLOOKUP(Tabela1[[#This Row],[MUNICÍPIO]],referencias!C:C,referencias!B:B,"não consta") -> SERTÃO PRODUTIVO | E142: IMPLANTAÇÃO DO SIAA - SISTEMA INTEGRADO DE ABASTECIMENTO DE ÁGUA NAS LOCALIDADES DE: BARRINHA, PATOS E AMOLA FACA | G142: 7635332.8 | H142: Ato dezembro Publicado
A143: Dezembro | B143: SEINFRA | C143: LIVRAMENTO DE NOSSA SENHORA | D143: =_xlfn.XLOOKUP(Tabela1[[#This Row],[MUNICÍPIO]],referencias!C:C,referencias!B:B,"não consta") -> SERTÃO PRODUTIVO | E143: CONSTRUÇÃO DE PONTE SOBRE O RIO DO PAULO NA RODOVIA BA-569, TRECHO: RIO DO PAULO, BA-569 COMUNIDADE DO TABULEIRO | F143: Ordem de Serviço | G143: 2409770.6 | H143: Ato dezembro Publicado
A144: Dezembro | B144: EMBASA | C144: LIVRAMENTO DE NOSSA SENHORA | D144: =_xlfn.XLOOKUP(Tabela1[[#This Row],[MUNICÍPIO]],referencias!C:C,referencias!B:B,"não consta") -> SERTÃO PRODUTIVO | E144: IMPLANTAÇÃO DO SISTEMA DE ABASTECIMENTO DA LOCALIDADES RURAL LAGOA DE DANIEL | F144: CONTRATO | G144: 552325.3 | H144: Ato dezembro Publicado
A145: Dezembro | B145: EMBASA | C145: LIVRAMENTO DE NOSSA SENHORA | D145: =_xlfn.XLOOKUP(Tabela1[[#This Row],[MUNICÍPIO]],referencias!C:C,referencias!B:B,"não consta") -> SERTÃO PRODUTIVO | E145: IMPLANTAÇÃO DO SISTEMA DE ABASTECIMENTO DA LOCALIDADES RURAL FAZENDA MATA | F145: CONTRATO | G145: 248203.55 | H145: Ato dezembro Publicado
A146: Dezembro | B146: SESAB | C146: MACAUBAS | D146: =_xlfn.XLOOKUP(Tabela1[[#This Row],[MUNICÍPIO]],referencias!C:C,referencias!B:B,"não consta") -> BACIA DO PARAMIRIM | E146: EQUIPAMENTOS DE SAÚDE | F146: CONVÊNIO | G146: 400000 | H146: Ato dezembro Publicado
A147: Dezembro | B147: CAR | C147: MACURURE | D147: =_xlfn.XLOOKUP(Tabela1[[#This Row],[MUNICÍPIO]],referencias!C:C,referencias!B:B,"não consta") -> não consta | E147: REFORMA DO MERCADO | F147: CONVÊNIO | G147: 2500009.4 | H147: Ato dezembro Publicado
A148: Dezembro | B148: CAR | C148: MAIRI | D148: =_xlfn.XLOOKUP(Tabela1[[#This Row],[MUNICÍPIO]],referencias!C:C,referencias!B:B,"não consta") -> BACIA DO JACUÍPE | E148: REFORMA DO MERCADO MUNICIPAL NO DISTRITO DE ANGICO | F148: LICITAÇÃO | G148: 2760417 | H148: Ato dezembro Publicado
A149: Dezembro | B149: SESAB | C149: MANSIDAO | D149: =_xlfn.XLOOKUP(Tabela1[[#This Row],[MUNICÍPIO]],referencias!C:C,referencias!B:B,"não consta") -> não consta | E149: CONSTRUÇÃO DE UBS | F149: CONVÊNIO | G149: 1870068.6 | H149: Ato dezembro Publicado
A150: Dezembro | B150: EMBASA | C150: MARAGOGIPE | D150: =_xlfn.XLOOKUP(Tabela1[[#This Row],[MUNICÍPIO]],referencias!C:C,referencias!B:B,"não consta") -> RECÔNCAVO | E150: IMPLANTAÇÃO DO SAA DE CAPANEMA | F150: CONTRATO | G150: 4928935.9 | H150: Ato dezembro Publicado
A151: Dezembro | B151: SEC | C151: MARAGOGIPE | D151: =_xlfn.XLOOKUP(Tabela1[[#This Row],[MUNICÍPIO]],referencias!C:C,referencias!B:B,"não consta") -> RECÔNCAVO | E151: AQUISIÇÃO DE APARELHOS DE ARES-CONDICIONADOS E MOBILIÁRIO ESCOLAR | F151: CONVÊNIO | G151: 127781.94 | H151: Ato dezembro Publicado
A152: Dezembro | B152: CAR | C152: MARCIONILIO SOUZA | D152: =_xlfn.XLOOKUP(Tabela1[[#This Row],[MUNICÍPIO]],referencias!C:C,referencias!B:B,"não consta") -> CHAPADA DIAMANTINA | E152: AMPLIAÇÃO DA COBERTURA LATERAL DO MERCADO MUNICIPAL | F152: CONVÊNIO | G152: 692657.27 | H152: Ato dezembro Publicado
A153: VISITA AO MUNICÍPIO | B153: CONDER | C153: ADUSTINA | D153: =_xlfn.XLOOKUP(Tabela1[[#This Row],[MUNICÍPIO]],referencias!C:C,referencias!B:B,"não consta") -> SEMIÁRIDO NORDESTE II | E153: CELEBRAR CONVÊNIO PARA CALÇAMENTO EM DIVERSAS RUAS NA SEDE | F153: Assina Autorização | G153: 0 | H153: Pleito em aberto
B154: CONDER | C154: ADUSTINA | D154: =_xlfn.XLOOKUP(Tabela1[[#This Row],[MUNICÍPIO]],referencias!C:C,referencias!B:B,"não consta") -> SEMIÁRIDO NORDESTE II | E154: Requalificação e Urbanização da entrada da Cidade, Contemplando Execução de Pórtico e Reforma do Canteiro Central, na Sede | G154: 0 | H154: Pleito em aberto
A155: Dezembro | B155: SEINFRA | C155: MUNDO NOVO | D155: =_xlfn.XLOOKUP(Tabela1[[#This Row],[MUNICÍPIO]],referencias!C:C,referencias!B:B,"não consta") -> PIEMONTE DO PARAGUAÇU | E155: PAVIMENTAÇÃO EM TSD NA RODOVIA BA-424, TRECHO: MUNDO NOVO- POVOADO DE COBÉ | F155: CONTRATO | G155: 4000000 | H155: Ato dezembro Publicado
A156: Dezembro | B156: CAR | C156: MUNDO NOVO | D156: =_xlfn.XLOOKUP(Tabela1[[#This Row],[MUNICÍPIO]],referencias!C:C,referencias!B:B,"não consta") -> PIEMONTE DO PARAGUAÇU | E156: REFORMA DO MERCADO | F156: CONVÊNIO | G156: 2132335.3 | H156: Ato dezembro Publicado
A157: 46174 | B157: CONDER | C157: ÁGUA FRIA | D157: =_xlfn.XLOOKUP(Tabela1[[#This Row],[MUNICÍPIO]],referencias!C:C,referencias!B:B,"não consta") -> PORTAL DO SERTÃO | E157: PAVIMENTAÇÃO ASFÁLTICA SOBRE PARALELO EM RUAS DO DISTRITO DE PATAÍBA E VIAS DA SEDE | F157: CONVÊNIO | G157: 3635229.2 | H157: Ato junho publicado
A158: VISITA AO MUNICÍPIO | B158: CONDER | C158: AIQUARA | D158: =_xlfn.XLOOKUP(Tabela1[[#This Row],[MUNICÍPIO]],referencias!C:C,referencias!B:B,"não consta") -> MÉDIO RIO DE CONTAS | E158: Elaborar Projeto para Construção de 11 Unidades Habitacionais Rurais na Comunidade de Pindorama - imediações das Fazendas São Jorge e Bela Vista | F158: Autoriza Elaboração de Projeto | G158: 0 | H158: Pleito em aberto
A159: Dezembro | B159: SEINFRA | C159: MUTUIPE | D159: =_xlfn.XLOOKUP(Tabela1[[#This Row],[MUNICÍPIO]],referencias!C:C,referencias!B:B,"não consta") -> VALE DO JIQUIRIÇÁ | E159: Publicação do edital de licitação para pavimentação em CBUQ, trecho Mutuípe – Distrito de Serra Grande (Valença). Extensão: 11,64 km | F159: LICITAÇÃO | G159: 22385156 | H159: Ato dezembro Publicado
A160: Dezembro | B160: CAR | C160: MUTUIPE | D160: =_xlfn.XLOOKUP(Tabela1[[#This Row],[MUNICÍPIO]],referencias!C:C,referencias!B:B,"não consta") -> VALE DO JIQUIRIÇÁ | E160: REFORMA DA FEIRA LIVRE | F160: CONVÊNIO | G160: 2249882.8 | H160: Ato dezembro Publicado
A161: Dezembro | B161: SEC | C161: NAZARE | D161: =_xlfn.XLOOKUP(Tabela1[[#This Row],[MUNICÍPIO]],referencias!C:C,referencias!B:B,"não consta") -> RECÔNCAVO | E161: AQUISIÇÃO DE EQUIPAMENTOS E MOBILIÁRIO ESCOLAR | F161: CONVÊNIO | G161: 356611.02 | H161: Ato dezembro Publicado
A162: Dezembro | B162: CAR | C162: NOVA CANAA | D162: =_xlfn.XLOOKUP(Tabela1[[#This Row],[MUNICÍPIO]],referencias!C:C,referencias!B:B,"não consta") -> MÉDIO SUDOESTE DA BAHIA | E162: REFORMA DO MERCADO PÚBLICO | F162: CONVÊNIO | G162: 3019345.2 | H162: Ato dezembro Publicado
A163: Dezembro | B163: CAR | C163: NOVA CANAA | D163: =_xlfn.XLOOKUP(Tabela1[[#This Row],[MUNICÍPIO]],referencias!C:C,referencias!B:B,"não consta") -> MÉDIO SUDOESTE DA BAHIA | E163: REFORMA DO MERCADO DE CARNE | F163: CONVÊNIO | H163: Ato dezembro Publicado
A164: Dezembro | B164: SEINFRA | C164: NOVA IBIÁ | D164: =_xlfn.XLOOKUP(Tabela1[[#This Row],[MUNICÍPIO]],referencias!C:C,referencias!B:B,"não consta") -> não consta | E164: PAVIMENTAÇÃO EM CBUQ DA RODOVIA BA-537, TRECHO: NOVA IBIÁ x ITAMARI | F164: CONTRATO | G164: 10996137 | H164: Ato dezembro Publicado
A165: VISITA AO MUNICÍPIO | B165: CONDER | C165: AIQUARA | D165: =_xlfn.XLOOKUP(Tabela1[[#This Row],[MUNICÍPIO]],referencias!C:C,referencias!B:B,"não consta") -> MÉDIO RIO DE CONTAS | E165: REALIZAÇÃO DE ESTUDO, IDENTIFICAÇÃO E CADASTRO DAS FAMÍLIAS EM SITUAÇÃO DE VULNERABILIDADE RESIDENTES NAS MARGENS DO RIO DE CONTAS NO DISTRITO DE PALMEIRINHA, VISANDO A CONSTRUÇÃO DE 16 UNIDADES HABITACIONAIS | F165: ASSINA AUTORIZAÇÃO | G165: 0 | H165: Pleito em aberto
A166: VISITA AO MUNICÍPIO | B166: CONDER | C166: ALAGOINHAS | D166: =_xlfn.XLOOKUP(Tabela1[[#This Row],[MUNICÍPIO]],referencias!C:C,referencias!B:B,"não consta") -> LITORAL NORTE E AGRESTE BAIANO | E166: DEFLAGRAR PROCESSO LICITATÓRIO PARA REQUALIFICAÇÃO DO ACESSO AO VIADUTO DA RUA DO CATU | F166: Autoriza Celebrar Convênio | G166: 9709876.2 | H166: ATENDIDO
...

Sheet referencias
A1: re | B1: Território | C1: Municipio
A2: 385 | B2: CHAPADA DIAMANTINA | C2: Abaíra
A3: 188 | B3: ITAPARICA | C3: Abaré
A4: 259 | B4: LITORAL NORTE E AGRESTE BAIANO | C4: Acajutiba
A5: 247 | B5: SEMIÁRIDO NORDESTE II | C5: Adustina
A6: 241 | B6: PORTAL DO SERTÃO | C6: Água Fria
A7: 409 | B7: MÉDIO RIO DE CONTAS | C7: Aiquara
A8: 12 | B8: LITORAL NORTE E AGRESTE BAIANO | C8: Alagoinhas
A9: 121 | B9: EXTREMO SUL | C9: Alcobaca
A10: 405 | B10: LITORAL SUL | C10: Almadina
A11: 68 | B11: VALE DO JIQUIRIÇÁ | C11: Amargosa
A12: 133 | B12: PORTAL DO SERTÃO | C12: Amélia Rodrigues
A13: 233 | B13: IRECÊ | C13: América Dourada
... A418: 50 | B418: IRECÊ | C418: Xique-Xique
